qat/__init__.py
qat/bdd_hooks.py
qat/qat.py
qat/qt_types.py
qat/report.py
qat/test_settings.py
qat/gui/__init__.py
qat/gui/dialogs.py
qat/gui/image_loader.py
qat/gui/launcher.py
qat/gui/stack_layout.py
qat/gui/theme.json
qat/gui/toolbar_items.py
qat/gui/application_manager/__init__.py
qat/gui/application_manager/editor.py
qat/gui/application_manager/toolbar.py
qat/gui/application_manager/window.py
qat/gui/images/add_icon.png
qat/gui/images/attach_icon.png
qat/gui/images/delete_icon.png
qat/gui/images/icon.png
qat/gui/images/qat_icon.ico
qat/gui/images/refresh_icon.png
qat/gui/images/spy_icon.png
qat/gui/images/start_icon.png
qat/gui/images/up_icon.png
qat/gui/spy/__init__.py
qat/gui/spy/object_tree.py
qat/gui/spy/property_table.py
qat/gui/spy/toolbar.py
qat/gui/spy/window.py
qat/internal/__init__.py
qat/internal/app_launcher.py
qat/internal/application_context.py
qat/internal/binding.py
qat/internal/communication_operations.py
qat/internal/debug_operations.py
qat/internal/find_object.py
qat/internal/gesture_operations.py
qat/internal/global_constants.py
qat/internal/global_state.py
qat/internal/keyboard_operations.py
qat/internal/mouse_operations.py
qat/internal/preferences.py
qat/internal/qat_color.py
qat/internal/qat_environment.py
qat/internal/qt_custom_object.py
qat/internal/qt_method.py
qat/internal/qt_object.py
qat/internal/screenshot_operations.py
qat/internal/synchronization.py
qat/internal/tcp_client.py
qat/internal/tcp_server.py
qat/internal/touch_operations.py
qat/internal/xml_report.py
qat/bin/QatServer.5.15.dll
qat/bin/QatServer.6.10.dll
qat/bin/QatServer.6.2.dll
qat/bin/QatServer.6.3.dll
qat/bin/QatServer.6.4.dll
qat/bin/QatServer.6.5.dll
qat/bin/QatServer.6.6.dll
qat/bin/QatServer.6.7.dll
qat/bin/QatServer.6.8.dll
qat/bin/QatServer.6.9.dll
qat/bin/injector.dll
qat/bin/injector.exe
qat/bin/libQatServer.5.15.dylib
qat/bin/libQatServer.5.15.so
qat/bin/libQatServer.6.10.dylib
qat/bin/libQatServer.6.10.so
qat/bin/libQatServer.6.2.dylib
qat-1.6.0.dist-info/METADATA
qat-1.6.0.dist-info/WHEEL
qat-1.6.0.dist-info/entry_points.txt
qat-1.6.0.dist-info/licenses/LICENSE.MIT
qat-1.6.0.dist-info/RECORD
