Metadata-Version: 2.4
Name: qat
Version: 1.6.0
Summary: Qt Application Tester, a BDD-oriented framework to test Qt-based applications
Project-URL: Changelog, https://qat.readthedocs.io/en/stable/CHANGELOG.html
Project-URL: Documentation, https://qat.readthedocs.io/en/stable/
Project-URL: Homepage, https://gitlab.com/testing-tool/qat
Project-URL: Issues, https://gitlab.com/testing-tool/qat/-/issues
Project-URL: Repository, https://gitlab.com/testing-tool/qat.git
Author-email: Quentin Derouault <qat.authors@gmail.com>
Maintainer-email: Quentin Derouault <qat.authors@gmail.com>
License-File: LICENSE.MIT
Keywords: BDD,Behaviour Driven Development,PyQt,PySide,qt,test,testing
Classifier: Development Status :: 5 - Production/Stable
Classifier: Intended Audience :: Developers
Classifier: License :: OSI Approved :: MIT License
Classifier: Natural Language :: English
Classifier: Operating System :: MacOS
Classifier: Operating System :: Microsoft :: Windows
Classifier: Operating System :: POSIX :: Linux
Classifier: Programming Language :: C++
Classifier: Programming Language :: Python :: 3
Classifier: Topic :: Software Development :: Testing
Classifier: Topic :: Software Development :: Testing :: BDD
Requires-Python: >=3.9
Requires-Dist: behave
Requires-Dist: customtkinter
Requires-Dist: pillow>=10.0.0
Requires-Dist: tkinter-tooltip
Requires-Dist: xmlschema
